ghtopdep/__version__.py
ghtopdep/ghtopdep.py
ghtopdep-0.4.3.dist-info/LICENSE
ghtopdep-0.4.3.dist-info/METADATA
ghtopdep-0.4.3.dist-info/WHEEL
ghtopdep-0.4.3.dist-info/entry_points.txt
ghtopdep-0.4.3.dist-info/RECORD
