Metadata-Version: 2.1
Name: ghtopdep
Version: 0.4.3
Summary: CLI tool for sorting dependents repositories and packages by stars
License: MIT
Author: Andriy Orehov
Author-email: andriyorehov@gmail.com
Requires-Python: >=3.7,<4.0
Classifier: License :: OSI Approved :: MIT License
Classifier: Programming Language :: Python :: 3
Classifier: Programming Language :: Python :: 3.7
Classifier: Programming Language :: Python :: 3.8
Classifier: Programming Language :: Python :: 3.9
Classifier: Programming Language :: Python :: 3.10
Classifier: Programming Language :: Python :: 3.11
Classifier: Programming Language :: Python :: 3.12
Requires-Dist: appdirs (>=1.4.4,<2.0.0)
Requires-Dist: cachecontrol[filecache] (>=0.14.0,<0.15.0)
Requires-Dist: click (>=8.1.2,<9.0.0)
Requires-Dist: github3.py (>=4.0.1,<5.0.0)
Requires-Dist: pipdate (>=0.5.6,<0.6.0)
Requires-Dist: requests (>=2.22,<3.0)
Requires-Dist: selectolax (>=0.3.7,<0.4.0)
Requires-Dist: tabulate (>=0.8.3,<0.9.0)
Requires-Dist: tqdm (>=4.66.4,<5.0.0)
Project-URL: Bug Tracker, https://github.com/github-tooling/ghtopdep/issues
Project-URL: Source, https://github.com/github-tooling/ghtopdep
